bag/__init__.py
bag/api/__init__.py
bag/api/main.py
bag/bricks/__init__.py
bag/bricks/foundation.py
bag/bricks/processor.py
bag/bricks/prompt.py
bag/bricks/router.py
bag/bricks/types.py
bag/cli/__init__.py
bag/cli/main.py
bag/core/__init__.py
bag/core/brick.py
bag/core/config_loader.py
bag/core/graph.py
bag/core/litellm_manager.py
bag/core/node.py
bag/core/types.py
bricks_and_graphs-0.1.1.dist-info/METADATA
bricks_and_graphs-0.1.1.dist-info/WHEEL
bricks_and_graphs-0.1.1.dist-info/entry_points.txt
bricks_and_graphs-0.1.1.dist-info/licenses/LICENSE
bricks_and_graphs-0.1.1.dist-info/RECORD
