Metadata-Version: 2.4
Name: bricks-and-graphs
Version: 0.1.1
Summary: An collaborative agentic framework for designing dynamic AI agents that can work together to resolve complex problems.
Project-URL: Homepage, https://github.com/wheredatalives/bricks-and-graphs
Project-URL: Repository, https://github.com/wheredatalives/bricks-and-graphs
Author-email: Igor <igor@allthedata.ai>
License-Expression: MIT
License-File: LICENSE
Classifier: Development Status :: 3 - Alpha
Classifier: Intended Audience :: Developers
Classifier: License :: OSI Approved :: MIT License
Classifier: Programming Language :: Python :: 3
Classifier: Programming Language :: Python :: 3.12
Classifier: Programming Language :: Python :: 3.13
Requires-Python: >=3.12
Requires-Dist: anthropic>=0.40.0
Requires-Dist: click>=8.1.0
Requires-Dist: fastapi>=0.104.0
Requires-Dist: litellm>=1.76.3
Requires-Dist: nest-asyncio>=1.5.0
Requires-Dist: networkx>=3.2.0
Requires-Dist: openai>=1.106.1
Requires-Dist: pandas>=2.1.0
Requires-Dist: polars>=0.20.0
Requires-Dist: pyarrow>=14.0.0
Requires-Dist: pydantic-settings>=2.1.0
Requires-Dist: pydantic>=2.5.0
Requires-Dist: pyyaml>=6.0.1
Requires-Dist: rich>=13.7.0
Requires-Dist: tenacity>=8.2.0
Requires-Dist: typing-extensions>=4.8.0
Requires-Dist: uvicorn[standard]>=0.24.0
Provides-Extra: dev
Requires-Dist: black>=23.11.0; extra == 'dev'
Requires-Dist: isort>=5.12.0; extra == 'dev'
Requires-Dist: mypy>=1.7.0; extra == 'dev'
Requires-Dist: pre-commit>=3.5.0; extra == 'dev'
Requires-Dist: pytest-asyncio>=0.21.0; extra == 'dev'
Requires-Dist: pytest-cov>=6.3.0; extra == 'dev'
Requires-Dist: pytest>=8.4.2; extra == 'dev'
Requires-Dist: ruff>=0.12.12; extra == 'dev'
Requires-Dist: twine>=5.1.0; extra == 'dev'
Provides-Extra: test
Requires-Dist: httpx>=0.25.0; extra == 'test'
Requires-Dist: pytest-asyncio>=1.1.0; extra == 'test'
Requires-Dist: pytest-cov>=6.2.1; extra == 'test'
Requires-Dist: pytest>=8.4.1; extra == 'test'
